auto_feature/.DS_Store
auto_feature/Dockerfile
auto_feature/Untitled.ipynb
auto_feature/__init__.py
auto_feature/auto_helper.ipynb
auto_feature/cli.py
auto_feature/dbhelper.py
auto_feature/docker-compose.yml
auto_feature/ftools.py
auto_feature/get_config.py
auto_feature/get_ft_features.py
auto_feature/helper.py
auto_feature/path.json
auto_feature/pivoting_automation.ipynb
auto_feature/requirements.txt
auto_feature/run.py
auto_feature/run_docker.sh
auto_feature/views.py
auto_feature/.ipynb_checkpoints/Untitled-checkpoint.ipynb
auto_feature/.ipynb_checkpoints/auto_helper-checkpoint.ipynb
auto_feature/.ipynb_checkpoints/pivoting_automation-checkpoint.ipynb
auto_feature/__pycache__/__init__.cpython-38.pyc
auto_feature/__pycache__/dbhelper.cpython-36.pyc
auto_feature/__pycache__/dbhelper.cpython-38.pyc
auto_feature/__pycache__/ftools.cpython-36.pyc
auto_feature/__pycache__/ftools.cpython-38.pyc
auto_feature/__pycache__/get_config.cpython-36.pyc
auto_feature/__pycache__/get_config.cpython-38.pyc
auto_feature/__pycache__/get_ft_features.cpython-36.pyc
auto_feature/__pycache__/get_ft_features.cpython-38.pyc
auto_feature/__pycache__/helper.cpython-36.pyc
auto_feature/__pycache__/helper.cpython-38.pyc
auto_feature/__pycache__/run.cpython-38.pyc
auto_feature/__pycache__/views.cpython-38.pyc
auto_feature/static/.DS_Store
auto_feature/static/css/Search-icon.png
auto_feature/static/css/bootstrap.min.css
auto_feature/static/css/chosen.css
auto_feature/static/css/chosen.min.css
auto_feature/static/css/favicon.png
auto_feature/static/css/ie10-viewport-bug-workaround.css
auto_feature/static/css/searchicon.png
auto_feature/static/css/selection.css
auto_feature/static/css/sticky-footer-navbar.css
auto_feature/static/css/style.css
auto_feature/static/display/.DS_Store
auto_feature/static/js/.DS_Store
auto_feature/static/js/BsMultiSelect.js
auto_feature/static/js/bootstrap.min.js
auto_feature/static/js/chosen.jquery.js
auto_feature/static/js/chosen.jquery.min.js
auto_feature-0.11.11.dist-info/METADATA
auto_feature-0.11.11.dist-info/WHEEL
auto_feature-0.11.11.dist-info/entry_points.txt
auto_feature-0.11.11.dist-info/top_level.txt
auto_feature-0.11.11.dist-info/RECORD
